<annotation>
	<folder>car1</folder>
	<filename>12930.jpg</filename>
	<path>F:\data\car1\12930.jpg</path>
	<source>
		<database>Unknown</database>
	</source>
	<size>
		<width>1920</width>
		<height>1080</height>
		<depth>3</depth>
	</size>
	<segmented>0</segmented>
	<object>
		<name>car</name>
		<pose>Unspecified</pose>
		<truncated>0</truncated>
		<difficult>0</difficult>
		<bndbox>
			<xmin>671</xmin>
			<ymin>566</ymin>
			<xmax>1177</xmax>
			<ymax>914</ymax>
		</bndbox>
	</object>
	<object>
		<name>car</name>
		<pose>Unspecified</pose>
		<truncated>0</truncated>
		<difficult>0</difficult>
		<bndbox>
			<xmin>959</xmin>
			<ymin>530</ymin>
			<xmax>986</xmax>
			<ymax>544</ymax>
		</bndbox>
	</object>
	<object>
		<name>car</name>
		<pose>Unspecified</pose>
		<truncated>0</truncated>
		<difficult>0</difficult>
		<bndbox>
			<xmin>988</xmin>
			<ymin>521</ymin>
			<xmax>1012</xmax>
			<ymax>537</ymax>
		</bndbox>
	</object>
</annotation>
